{
  "characteristics": {
    "cpu": 0.088628, 
    "gpu_copy": 0.049582, 
    "gpu_only": 0.047399, 
    "is_gpu_better": true, 
    "l2 cache and mmu counters": {
      "0": 1538677822, 
      "1": 23, 
      "10": 0, 
      "11": 0, 
      "12": 0, 
      "13": 0, 
      "14": 0, 
      "15": 0, 
      "16": 8, 
      "17": 3, 
      "18": 139, 
      "19": 4, 
      "2": 65535, 
      "20": 0, 
      "21": 0, 
      "22": 0, 
      "23": 0, 
      "24": 0, 
      "25": 0, 
      "26": 0, 
      "27": 0, 
      "28": 0, 
      "29": 0, 
      "3": 0, 
      "30": 8170, 
      "31": 54948, 
      "32": 9300188, 
      "33": 7684727, 
      "34": 7679357, 
      "35": 633762, 
      "36": 691810, 
      "37": 7434266, 
      "38": 0, 
      "39": 914646, 
      "4": 1140, 
      "40": 887549, 
      "41": 2097, 
      "42": 0, 
      "43": 912426, 
      "44": 0, 
      "45": 96, 
      "46": 0, 
      "47": 0, 
      "48": 13737, 
      "49": 13737, 
      "5": 58, 
      "50": 2048, 
      "51": 1867, 
      "52": 7, 
      "53": 2, 
      "54": 0, 
      "55": 0, 
      "56": 0, 
      "57": 151, 
      "58": 0, 
      "59": 0, 
      "6": 35, 
      "60": 0, 
      "61": 230656, 
      "62": 7940865, 
      "63": 6448019, 
      "7": 92, 
      "8": 42, 
      "9": 0
    }, 
    "shader core counters": {
      "0": [
        1538677822, 
        1538677822, 
        1538677822, 
        1538677822
      ], 
      "1": [
        23, 
        23, 
        23, 
        23
      ], 
      "10": [
        0, 
        0, 
        0, 
        0
      ], 
      "11": [
        0, 
        0, 
        0, 
        0
      ], 
      "12": [
        0, 
        0, 
        0, 
        0
      ], 
      "13": [
        0, 
        0, 
        0, 
        0
      ], 
      "14": [
        0, 
        0, 
        0, 
        0
      ], 
      "15": [
        0, 
        0, 
        0, 
        0
      ], 
      "16": [
        0, 
        0, 
        0, 
        0
      ], 
      "17": [
        0, 
        0, 
        0, 
        0
      ], 
      "18": [
        0, 
        0, 
        0, 
        0
      ], 
      "19": [
        0, 
        0, 
        0, 
        0
      ], 
      "2": [
        65535, 
        65535, 
        65535, 
        65535
      ], 
      "20": [
        0, 
        0, 
        0, 
        0
      ], 
      "21": [
        0, 
        0, 
        0, 
        0
      ], 
      "22": [
        12607919, 
        12602636, 
        12599105, 
        12606052
      ], 
      "23": [
        2719, 
        2031, 
        2650, 
        792
      ], 
      "24": [
        348032, 
        259968, 
        339200, 
        101376
      ], 
      "25": [
        112693, 
        249434, 
        140805, 
        1019708
      ], 
      "26": [
        12607564, 
        12602278, 
        12598754, 
        12605705
      ], 
      "27": [
        6206171, 
        4692307, 
        6003760, 
        1898890
      ], 
      "28": [
        369132, 
        225113, 
        343258, 
        98953
      ], 
      "29": [
        5928669, 
        6892411, 
        6127779, 
        5151931
      ], 
      "3": [
        0, 
        0, 
        0, 
        0
      ], 
      "30": [
        0, 
        0, 
        0, 
        0
      ], 
      "31": [
        4158614, 
        3201526, 
        4039780, 
        1387542
      ], 
      "32": [
        9010064, 
        10923081, 
        9411543, 
        12265156
      ], 
      "33": [
        0, 
        0, 
        0, 
        0
      ], 
      "34": [
        4851450, 
        7721555, 
        5371763, 
        10877614
      ], 
      "35": [
        0, 
        0, 
        0, 
        0
      ], 
      "36": [
        0, 
        0, 
        0, 
        0
      ], 
      "37": [
        0, 
        0, 
        0, 
        0
      ], 
      "38": [
        0, 
        0, 
        0, 
        0
      ], 
      "39": [
        0, 
        0, 
        0, 
        0
      ], 
      "4": [
        0, 
        0, 
        0, 
        0
      ], 
      "40": [
        0, 
        0, 
        0, 
        0
      ], 
      "41": [
        0, 
        0, 
        0, 
        0
      ], 
      "42": [
        0, 
        0, 
        0, 
        0
      ], 
      "43": [
        0, 
        0, 
        0, 
        0
      ], 
      "44": [
        0, 
        0, 
        0, 
        0
      ], 
      "45": [
        0, 
        0, 
        0, 
        0
      ], 
      "46": [
        0, 
        0, 
        0, 
        0
      ], 
      "47": [
        0, 
        0, 
        0, 
        0
      ], 
      "48": [
        673464, 
        503098, 
        651582, 
        195280
      ], 
      "49": [
        187792, 
        548284, 
        267461, 
        918707
      ], 
      "5": [
        0, 
        0, 
        0, 
        0
      ], 
      "50": [
        515711, 
        408960, 
        502512, 
        194769
      ], 
      "51": [
        26057, 
        16491, 
        24215, 
        4001
      ], 
      "52": [
        515711, 
        408960, 
        502512, 
        194769
      ], 
      "53": [
        971905, 
        2153834, 
        1159377, 
        3628609
      ], 
      "54": [
        279030, 
        226199, 
        270813, 
        113709
      ], 
      "55": [
        1571, 
        1168, 
        1585, 
        436
      ], 
      "56": [
        218594, 
        175491, 
        210641, 
        88005
      ], 
      "57": [
        1, 
        1, 
        1, 
        1
      ], 
      "58": [
        3, 
        3, 
        3, 
        3
      ], 
      "59": [
        47, 
        47, 
        48, 
        47
      ], 
      "6": [
        0, 
        0, 
        0, 
        0
      ], 
      "60": [
        157, 
        121, 
        145, 
        133
      ], 
      "61": [
        1704887, 
        1321018, 
        1656607, 
        584819
      ], 
      "62": [
        372, 
        372, 
        372, 
        372
      ], 
      "63": [
        8, 
        0, 
        8, 
        0
      ], 
      "7": [
        0, 
        0, 
        0, 
        0
      ], 
      "8": [
        0, 
        0, 
        0, 
        0
      ], 
      "9": [
        0, 
        0, 
        0, 
        0
      ]
    }
  }, 
  "features": {
    "GWS": [
      12, 
      12, 
      64
    ], 
    "LWS": [
      4, 
      1, 
      64
    ], 
    "OFFSET": [
      0, 
      0, 
      0
    ], 
    "compiler name": "ARM Mali OpenCL", 
    "compiler version": "5.0", 
    "cpu_freq": 1600, 
    "gpu_freq": 266, 
    "image cols": 807, 
    "image rows": 1142, 
    "pool_dir": "pool.08", 
    "program version": "c597087", 
    "size": 128
  }, 
  "meta": {
    "device name": "Mali-T604", 
    "device type": "GPU", 
    "device vendor": "ARM", 
    "experiment type": "benchmarking", 
    "kernel name": "calc_histogram", 
    "program name": "Realeyes HOG"
  }, 
  "tags": [
    "demo", 
    "arm", 
    "codegen15"
  ], 
  "work": {
    "repl": 3, 
    "timestamp": "2015-02-22T02:30:02.068498"
  }
}