{
  "characteristics": {
    "cpu": 0.035497, 
    "gpu_copy": 0.024179, 
    "gpu_only": 0.007983, 
    "is_gpu_better": true, 
    "l2 cache and mmu counters": {
      "0": 1707986541, 
      "1": 16, 
      "10": 0, 
      "11": 0, 
      "12": 0, 
      "13": 0, 
      "14": 0, 
      "15": 0, 
      "16": 9, 
      "17": 3, 
      "18": 156, 
      "19": 7, 
      "2": 65535, 
      "20": 0, 
      "21": 0, 
      "22": 0, 
      "23": 0, 
      "24": 0, 
      "25": 0, 
      "26": 0, 
      "27": 0, 
      "28": 0, 
      "29": 0, 
      "3": 0, 
      "30": 2529, 
      "31": 17224, 
      "32": 1517950, 
      "33": 1252421, 
      "34": 1249626, 
      "35": 100885, 
      "36": 112003, 
      "37": 1196654, 
      "38": 0, 
      "39": 148560, 
      "4": 15687, 
      "40": 143460, 
      "41": 618, 
      "42": 0, 
      "43": 148003, 
      "44": 0, 
      "45": 68, 
      "46": 0, 
      "47": 0, 
      "48": 4306, 
      "49": 4306, 
      "5": 348, 
      "50": 637, 
      "51": 548, 
      "52": 6, 
      "53": 2, 
      "54": 0, 
      "55": 0, 
      "56": 0, 
      "57": 0, 
      "58": 0, 
      "59": 0, 
      "6": 37, 
      "60": 0, 
      "61": 50595, 
      "62": 1241757, 
      "63": 1040494, 
      "7": 250, 
      "8": 320, 
      "9": 0
    }, 
    "shader core counters": {
      "0": [
        1707986541, 
        1707986541, 
        1707986541, 
        1707986541
      ], 
      "1": [
        16, 
        16, 
        16, 
        16
      ], 
      "10": [
        0, 
        0, 
        0, 
        0
      ], 
      "11": [
        0, 
        0, 
        0, 
        0
      ], 
      "12": [
        0, 
        0, 
        0, 
        0
      ], 
      "13": [
        0, 
        0, 
        0, 
        0
      ], 
      "14": [
        0, 
        0, 
        0, 
        0
      ], 
      "15": [
        0, 
        0, 
        0, 
        0
      ], 
      "16": [
        0, 
        0, 
        0, 
        0
      ], 
      "17": [
        0, 
        0, 
        0, 
        0
      ], 
      "18": [
        0, 
        0, 
        0, 
        0
      ], 
      "19": [
        0, 
        0, 
        0, 
        0
      ], 
      "2": [
        65535, 
        65535, 
        65535, 
        65535
      ], 
      "20": [
        0, 
        0, 
        0, 
        0
      ], 
      "21": [
        0, 
        0, 
        0, 
        0
      ], 
      "22": [
        2122798, 
        2116090, 
        2118531, 
        2123159
      ], 
      "23": [
        616, 
        542, 
        600, 
        290
      ], 
      "24": [
        78848, 
        69376, 
        76800, 
        37120
      ], 
      "25": [
        44740, 
        174994, 
        106764, 
        682826
      ], 
      "26": [
        2122334, 
        2115625, 
        2118069, 
        2122705
      ], 
      "27": [
        1147060, 
        1005636, 
        1108460, 
        542138
      ], 
      "28": [
        79618, 
        62635, 
        75021, 
        28416
      ], 
      "29": [
        861538, 
        952189, 
        871086, 
        891507
      ], 
      "3": [
        0, 
        0, 
        0, 
        0
      ], 
      "30": [
        0, 
        0, 
        0, 
        0
      ], 
      "31": [
        736358, 
        649188, 
        714920, 
        359828
      ], 
      "32": [
        1448995, 
        1619896, 
        1478181, 
        1843027
      ], 
      "33": [
        0, 
        0, 
        0, 
        0
      ], 
      "34": [
        712637, 
        970708, 
        763261, 
        1483199
      ], 
      "35": [
        0, 
        0, 
        0, 
        0
      ], 
      "36": [
        0, 
        0, 
        0, 
        0
      ], 
      "37": [
        0, 
        0, 
        0, 
        0
      ], 
      "38": [
        0, 
        0, 
        0, 
        0
      ], 
      "39": [
        0, 
        0, 
        0, 
        0
      ], 
      "4": [
        0, 
        0, 
        0, 
        0
      ], 
      "40": [
        0, 
        0, 
        0, 
        0
      ], 
      "41": [
        0, 
        0, 
        0, 
        0
      ], 
      "42": [
        0, 
        0, 
        0, 
        0
      ], 
      "43": [
        0, 
        0, 
        0, 
        0
      ], 
      "44": [
        0, 
        0, 
        0, 
        0
      ], 
      "45": [
        0, 
        0, 
        0, 
        0
      ], 
      "46": [
        0, 
        0, 
        0, 
        0
      ], 
      "47": [
        0, 
        0, 
        0, 
        0
      ], 
      "48": [
        134208, 
        116752, 
        129152, 
        62256
      ], 
      "49": [
        29165, 
        61331, 
        36366, 
        122091
      ], 
      "5": [
        0, 
        0, 
        0, 
        0
      ], 
      "50": [
        79373, 
        70869, 
        77568, 
        41151
      ], 
      "51": [
        3574, 
        2788, 
        3360, 
        1135
      ], 
      "52": [
        79373, 
        70869, 
        77568, 
        41151
      ], 
      "53": [
        172892, 
        276933, 
        192870, 
        510644
      ], 
      "54": [
        41845, 
        37391, 
        40272, 
        24696
      ], 
      "55": [
        477, 
        397, 
        427, 
        269
      ], 
      "56": [
        32705, 
        29105, 
        31440, 
        18931
      ], 
      "57": [
        1, 
        1, 
        1, 
        1
      ], 
      "58": [
        3, 
        3, 
        3, 
        3
      ], 
      "59": [
        49, 
        47, 
        48, 
        48
      ], 
      "6": [
        0, 
        0, 
        0, 
        0
      ], 
      "60": [
        2233, 
        1966, 
        2109, 
        1271
      ], 
      "61": [
        292955, 
        258490, 
        284288, 
        144558
      ], 
      "62": [
        372, 
        372, 
        372, 
        372
      ], 
      "63": [
        24, 
        0, 
        16, 
        16
      ], 
      "7": [
        0, 
        0, 
        0, 
        0
      ], 
      "8": [
        0, 
        0, 
        0, 
        0
      ], 
      "9": [
        0, 
        0, 
        0, 
        0
      ]
    }
  }, 
  "features": {
    "GWS": [
      64, 
      64, 
      64
    ], 
    "LWS": [
      4, 
      1, 
      64
    ], 
    "OFFSET": [
      0, 
      0, 
      0
    ], 
    "compiler name": "ARM Mali OpenCL", 
    "compiler version": "5.0", 
    "cpu_freq": 800, 
    "gpu_freq": 266, 
    "image cols": 3000, 
    "image rows": 1639, 
    "pool_dir": "pool.11", 
    "program version": "c597087", 
    "size": 64
  }, 
  "meta": {
    "device name": "Mali-T604", 
    "device type": "GPU", 
    "device vendor": "ARM", 
    "experiment type": "benchmarking", 
    "kernel name": "calc_histogram", 
    "program name": "Realeyes HOG"
  }, 
  "tags": [
    "demo", 
    "arm", 
    "codegen15"
  ], 
  "work": {
    "repl": 2, 
    "timestamp": "2015-02-22T02:09:16.552917"
  }
}