{
  "characteristics": {
    "cpu": 0.003274, 
    "gpu_copy": 0.015133, 
    "gpu_only": 0.000716, 
    "is_gpu_better": false, 
    "l2 cache and mmu counters": {
      "0": 3776553472, 
      "1": 17, 
      "10": 0, 
      "11": 0, 
      "12": 0, 
      "13": 0, 
      "14": 0, 
      "15": 0, 
      "16": 8, 
      "17": 3, 
      "18": 159, 
      "19": 4, 
      "2": 65535, 
      "20": 0, 
      "21": 0, 
      "22": 0, 
      "23": 0, 
      "24": 0, 
      "25": 0, 
      "26": 0, 
      "27": 0, 
      "28": 0, 
      "29": 0, 
      "3": 0, 
      "30": 814, 
      "31": 4480, 
      "32": 139515, 
      "33": 111414, 
      "34": 109845, 
      "35": 9357, 
      "36": 10007, 
      "37": 106662, 
      "38": 0, 
      "39": 13875, 
      "4": 1686, 
      "40": 13494, 
      "41": 97, 
      "42": 0, 
      "43": 13827, 
      "44": 0, 
      "45": 48, 
      "46": 0, 
      "47": 1, 
      "48": 1120, 
      "49": 1120, 
      "5": 265, 
      "50": 213, 
      "51": 186, 
      "52": 4, 
      "53": 2, 
      "54": 0, 
      "55": 0, 
      "56": 0, 
      "57": 0, 
      "58": 0, 
      "59": 0, 
      "6": 80, 
      "60": 0, 
      "61": 3579, 
      "62": 112330, 
      "63": 88429, 
      "7": 272, 
      "8": 242, 
      "9": 0
    }, 
    "shader core counters": {
      "0": [
        3776553472, 
        3776553472, 
        3776553472, 
        3776553472
      ], 
      "1": [
        17, 
        17, 
        17, 
        17
      ], 
      "10": [
        0, 
        0, 
        0, 
        0
      ], 
      "11": [
        0, 
        0, 
        0, 
        0
      ], 
      "12": [
        0, 
        0, 
        0, 
        0
      ], 
      "13": [
        0, 
        0, 
        0, 
        0
      ], 
      "14": [
        0, 
        0, 
        0, 
        0
      ], 
      "15": [
        0, 
        0, 
        0, 
        0
      ], 
      "16": [
        0, 
        0, 
        0, 
        0
      ], 
      "17": [
        0, 
        0, 
        0, 
        0
      ], 
      "18": [
        0, 
        0, 
        0, 
        0
      ], 
      "19": [
        0, 
        0, 
        0, 
        0
      ], 
      "2": [
        65535, 
        65535, 
        65535, 
        65535
      ], 
      "20": [
        0, 
        0, 
        0, 
        0
      ], 
      "21": [
        0, 
        0, 
        0, 
        0
      ], 
      "22": [
        187155, 
        190290, 
        189377, 
        182527
      ], 
      "23": [
        41, 
        33, 
        39, 
        15
      ], 
      "24": [
        5248, 
        4224, 
        4992, 
        1920
      ], 
      "25": [
        5447, 
        9355, 
        6813, 
        38550
      ], 
      "26": [
        186806, 
        189931, 
        189025, 
        182183
      ], 
      "27": [
        91180, 
        74060, 
        89534, 
        33406
      ], 
      "28": [
        5689, 
        3895, 
        5353, 
        1772
      ], 
      "29": [
        81208, 
        90538, 
        83061, 
        59128
      ], 
      "3": [
        0, 
        0, 
        0, 
        0
      ], 
      "30": [
        0, 
        0, 
        0, 
        0
      ], 
      "31": [
        59890, 
        49980, 
        58754, 
        24730
      ], 
      "32": [
        130969, 
        153651, 
        137020, 
        158945
      ], 
      "33": [
        0, 
        0, 
        0, 
        0
      ], 
      "34": [
        71079, 
        103671, 
        78266, 
        134215
      ], 
      "35": [
        0, 
        0, 
        0, 
        0
      ], 
      "36": [
        0, 
        0, 
        0, 
        0
      ], 
      "37": [
        0, 
        0, 
        0, 
        0
      ], 
      "38": [
        0, 
        0, 
        0, 
        0
      ], 
      "39": [
        0, 
        0, 
        0, 
        0
      ], 
      "4": [
        0, 
        0, 
        0, 
        0
      ], 
      "40": [
        0, 
        0, 
        0, 
        0
      ], 
      "41": [
        0, 
        0, 
        0, 
        0
      ], 
      "42": [
        0, 
        0, 
        0, 
        0
      ], 
      "43": [
        0, 
        0, 
        0, 
        0
      ], 
      "44": [
        0, 
        0, 
        0, 
        0
      ], 
      "45": [
        0, 
        0, 
        0, 
        0
      ], 
      "46": [
        0, 
        0, 
        0, 
        0
      ], 
      "47": [
        0, 
        0, 
        0, 
        0
      ], 
      "48": [
        9872, 
        8096, 
        9736, 
        3528
      ], 
      "49": [
        2980, 
        7229, 
        4091, 
        11013
      ], 
      "5": [
        0, 
        0, 
        0, 
        0
      ], 
      "50": [
        7260, 
        6199, 
        7148, 
        3410
      ], 
      "51": [
        357, 
        269, 
        329, 
        77
      ], 
      "52": [
        7260, 
        6199, 
        7148, 
        3410
      ], 
      "53": [
        13887, 
        26857, 
        16130, 
        43943
      ], 
      "54": [
        3973, 
        3671, 
        3989, 
        1929
      ], 
      "55": [
        23, 
        16, 
        23, 
        8
      ], 
      "56": [
        2990, 
        2706, 
        2934, 
        1381
      ], 
      "57": [
        1, 
        1, 
        1, 
        1
      ], 
      "58": [
        3, 
        3, 
        3, 
        3
      ], 
      "59": [
        47, 
        47, 
        47, 
        47
      ], 
      "6": [
        0, 
        0, 
        0, 
        0
      ], 
      "60": [
        216, 
        235, 
        243, 
        110
      ], 
      "61": [
        24393, 
        20494, 
        24033, 
        10349
      ], 
      "62": [
        372, 
        372, 
        372, 
        372
      ], 
      "63": [
        0, 
        0, 
        0, 
        0
      ], 
      "7": [
        0, 
        0, 
        0, 
        0
      ], 
      "8": [
        0, 
        0, 
        0, 
        0
      ], 
      "9": [
        0, 
        0, 
        0, 
        0
      ]
    }
  }, 
  "features": {
    "GWS": [
      16, 
      16, 
      64
    ], 
    "LWS": [
      4, 
      1, 
      64
    ], 
    "OFFSET": [
      0, 
      0, 
      0
    ], 
    "compiler name": "ARM Mali OpenCL", 
    "compiler version": "5.0", 
    "cpu_freq": 800, 
    "gpu_freq": 266, 
    "image cols": 2582, 
    "image rows": 1940, 
    "pool_dir": "pool.06", 
    "program version": "c597087", 
    "size": 16
  }, 
  "meta": {
    "device name": "Mali-T604", 
    "device type": "GPU", 
    "device vendor": "ARM", 
    "experiment type": "benchmarking", 
    "kernel name": "calc_histogram", 
    "program name": "Realeyes HOG"
  }, 
  "tags": [
    "demo", 
    "arm", 
    "codegen15"
  ], 
  "work": {
    "repl": 4, 
    "timestamp": "2015-02-22T02:13:41.667575"
  }
}