{
  "characteristics": {
    "cpu": 0.003227, 
    "gpu_copy": 0.014159, 
    "gpu_only": 0.000387, 
    "is_gpu_better": false, 
    "l2 cache and mmu counters": {
      "0": 3919533941, 
      "1": 17, 
      "10": 0, 
      "11": 0, 
      "12": 0, 
      "13": 0, 
      "14": 0, 
      "15": 0, 
      "16": 9, 
      "17": 3, 
      "18": 212, 
      "19": 5, 
      "2": 65535, 
      "20": 0, 
      "21": 0, 
      "22": 0, 
      "23": 0, 
      "24": 0, 
      "25": 0, 
      "26": 0, 
      "27": 0, 
      "28": 0, 
      "29": 0, 
      "3": 0, 
      "30": 826, 
      "31": 4688, 
      "32": 151029, 
      "33": 120800, 
      "34": 118565, 
      "35": 10147, 
      "36": 10793, 
      "37": 115915, 
      "38": 0, 
      "39": 15192, 
      "4": 1511, 
      "40": 14773, 
      "41": 104, 
      "42": 0, 
      "43": 15133, 
      "44": 0, 
      "45": 25, 
      "46": 0, 
      "47": 14, 
      "48": 1172, 
      "49": 1172, 
      "5": 171, 
      "50": 216, 
      "51": 180, 
      "52": 4, 
      "53": 2, 
      "54": 0, 
      "55": 0, 
      "56": 0, 
      "57": 39, 
      "58": 210, 
      "59": 0, 
      "6": 51, 
      "60": 0, 
      "61": 3614, 
      "62": 122675, 
      "63": 95104, 
      "7": 265, 
      "8": 143, 
      "9": 0
    }, 
    "shader core counters": {
      "0": [
        3919533941, 
        3919533941, 
        3919533941, 
        3919533941
      ], 
      "1": [
        17, 
        17, 
        17, 
        17
      ], 
      "10": [
        0, 
        0, 
        0, 
        0
      ], 
      "11": [
        0, 
        0, 
        0, 
        0
      ], 
      "12": [
        0, 
        0, 
        0, 
        0
      ], 
      "13": [
        0, 
        0, 
        0, 
        0
      ], 
      "14": [
        0, 
        0, 
        0, 
        0
      ], 
      "15": [
        0, 
        0, 
        0, 
        0
      ], 
      "16": [
        0, 
        0, 
        0, 
        0
      ], 
      "17": [
        0, 
        0, 
        0, 
        0
      ], 
      "18": [
        0, 
        0, 
        0, 
        0
      ], 
      "19": [
        0, 
        0, 
        0, 
        0
      ], 
      "2": [
        65535, 
        65535, 
        65535, 
        65535
      ], 
      "20": [
        0, 
        0, 
        0, 
        0
      ], 
      "21": [
        0, 
        0, 
        0, 
        0
      ], 
      "22": [
        200883, 
        205681, 
        206033, 
        202103
      ], 
      "23": [
        41, 
        34, 
        38, 
        15
      ], 
      "24": [
        5248, 
        4352, 
        4864, 
        1920
      ], 
      "25": [
        9012, 
        7405, 
        6951, 
        9212
      ], 
      "26": [
        200455, 
        205250, 
        205609, 
        201674
      ], 
      "27": [
        93552, 
        79076, 
        92960, 
        38840
      ], 
      "28": [
        5516, 
        3832, 
        5315, 
        1809
      ], 
      "29": [
        87348, 
        102780, 
        94910, 
        89324
      ], 
      "3": [
        0, 
        0, 
        0, 
        0
      ], 
      "30": [
        0, 
        0, 
        0, 
        0
      ], 
      "31": [
        62510, 
        53672, 
        62580, 
        27604
      ], 
      "32": [
        137794, 
        168483, 
        149236, 
        188151
      ], 
      "33": [
        0, 
        0, 
        0, 
        0
      ], 
      "34": [
        75284, 
        114811, 
        86656, 
        160547
      ], 
      "35": [
        0, 
        0, 
        0, 
        0
      ], 
      "36": [
        0, 
        0, 
        0, 
        0
      ], 
      "37": [
        0, 
        0, 
        0, 
        0
      ], 
      "38": [
        0, 
        0, 
        0, 
        0
      ], 
      "39": [
        0, 
        0, 
        0, 
        0
      ], 
      "4": [
        0, 
        0, 
        0, 
        0
      ], 
      "40": [
        0, 
        0, 
        0, 
        0
      ], 
      "41": [
        0, 
        0, 
        0, 
        0
      ], 
      "42": [
        0, 
        0, 
        0, 
        0
      ], 
      "43": [
        0, 
        0, 
        0, 
        0
      ], 
      "44": [
        0, 
        0, 
        0, 
        0
      ], 
      "45": [
        0, 
        0, 
        0, 
        0
      ], 
      "46": [
        0, 
        0, 
        0, 
        0
      ], 
      "47": [
        0, 
        0, 
        0, 
        0
      ], 
      "48": [
        10028, 
        8488, 
        10100, 
        3896
      ], 
      "49": [
        3813, 
        9586, 
        5087, 
        17025
      ], 
      "5": [
        0, 
        0, 
        0, 
        0
      ], 
      "50": [
        7784, 
        6800, 
        7846, 
        3881
      ], 
      "51": [
        378, 
        281, 
        362, 
        97
      ], 
      "52": [
        7784, 
        6800, 
        7846, 
        3881
      ], 
      "53": [
        13668, 
        28009, 
        17103, 
        47926
      ], 
      "54": [
        4253, 
        3974, 
        4461, 
        2142
      ], 
      "55": [
        18, 
        15, 
        23, 
        9
      ], 
      "56": [
        3146, 
        2840, 
        3293, 
        1526
      ], 
      "57": [
        1, 
        1, 
        1, 
        1
      ], 
      "58": [
        3, 
        3, 
        3, 
        3
      ], 
      "59": [
        48, 
        47, 
        47, 
        47
      ], 
      "6": [
        0, 
        0, 
        0, 
        0
      ], 
      "60": [
        201, 
        200, 
        233, 
        92
      ], 
      "61": [
        25597, 
        22088, 
        25792, 
        11658
      ], 
      "62": [
        372, 
        372, 
        372, 
        372
      ], 
      "63": [
        16, 
        0, 
        0, 
        0
      ], 
      "7": [
        0, 
        0, 
        0, 
        0
      ], 
      "8": [
        0, 
        0, 
        0, 
        0
      ], 
      "9": [
        0, 
        0, 
        0, 
        0
      ]
    }
  }, 
  "features": {
    "GWS": [
      16, 
      16, 
      64
    ], 
    "LWS": [
      4, 
      1, 
      64
    ], 
    "OFFSET": [
      0, 
      0, 
      0
    ], 
    "compiler name": "ARM Mali OpenCL", 
    "compiler version": "5.0", 
    "cpu_freq": 800, 
    "gpu_freq": 533, 
    "image cols": 1683, 
    "image rows": 2246, 
    "pool_dir": "pool.10", 
    "program version": "c597087", 
    "size": 16
  }, 
  "meta": {
    "device name": "Mali-T604", 
    "device type": "GPU", 
    "device vendor": "ARM", 
    "experiment type": "benchmarking", 
    "kernel name": "calc_histogram", 
    "program name": "Realeyes HOG"
  }, 
  "tags": [
    "demo", 
    "arm", 
    "codegen15"
  ], 
  "work": {
    "repl": 3, 
    "timestamp": "2015-02-22T02:13:47.628345"
  }
}