{
  "characteristics": {
    "cpu": 0.002693, 
    "gpu_copy": 0.014624, 
    "gpu_only": 0.000647, 
    "is_gpu_better": false, 
    "l2 cache and mmu counters": {
      "0": 1073514369, 
      "1": 10, 
      "10": 0, 
      "11": 0, 
      "12": 0, 
      "13": 0, 
      "14": 0, 
      "15": 0, 
      "16": 8, 
      "17": 3, 
      "18": 142, 
      "19": 4, 
      "2": 65535, 
      "20": 0, 
      "21": 0, 
      "22": 0, 
      "23": 0, 
      "24": 0, 
      "25": 0, 
      "26": 0, 
      "27": 0, 
      "28": 0, 
      "29": 0, 
      "3": 0, 
      "30": 814, 
      "31": 3888, 
      "32": 126069, 
      "33": 100684, 
      "34": 99397, 
      "35": 8474, 
      "36": 9098, 
      "37": 96451, 
      "38": 0, 
      "39": 12092, 
      "4": 1151, 
      "40": 11744, 
      "41": 96, 
      "42": 0, 
      "43": 12036, 
      "44": 0, 
      "45": 41, 
      "46": 0, 
      "47": 2, 
      "48": 972, 
      "49": 972, 
      "5": 142, 
      "50": 207, 
      "51": 180, 
      "52": 4, 
      "53": 2, 
      "54": 0, 
      "55": 0, 
      "56": 0, 
      "57": 0, 
      "58": 0, 
      "59": 0, 
      "6": 10, 
      "60": 0, 
      "61": 3179, 
      "62": 101893, 
      "63": 81682, 
      "7": 159, 
      "8": 119, 
      "9": 0
    }, 
    "shader core counters": {
      "0": [
        1073514369, 
        1073514369, 
        1073514369, 
        1073514369
      ], 
      "1": [
        10, 
        10, 
        10, 
        10
      ], 
      "10": [
        0, 
        0, 
        0, 
        0
      ], 
      "11": [
        0, 
        0, 
        0, 
        0
      ], 
      "12": [
        0, 
        0, 
        0, 
        0
      ], 
      "13": [
        0, 
        0, 
        0, 
        0
      ], 
      "14": [
        0, 
        0, 
        0, 
        0
      ], 
      "15": [
        0, 
        0, 
        0, 
        0
      ], 
      "16": [
        0, 
        0, 
        0, 
        0
      ], 
      "17": [
        0, 
        0, 
        0, 
        0
      ], 
      "18": [
        0, 
        0, 
        0, 
        0
      ], 
      "19": [
        0, 
        0, 
        0, 
        0
      ], 
      "2": [
        65535, 
        65535, 
        65535, 
        65535
      ], 
      "20": [
        0, 
        0, 
        0, 
        0
      ], 
      "21": [
        0, 
        0, 
        0, 
        0
      ], 
      "22": [
        165741, 
        170590, 
        172030, 
        171475
      ], 
      "23": [
        41, 
        34, 
        41, 
        12
      ], 
      "24": [
        5248, 
        4352, 
        5248, 
        1536
      ], 
      "25": [
        6846, 
        9588, 
        7692, 
        9481
      ], 
      "26": [
        165399, 
        170248, 
        171688, 
        171135
      ], 
      "27": [
        78988, 
        64048, 
        78436, 
        24472
      ], 
      "28": [
        4672, 
        3055, 
        4354, 
        1450
      ], 
      "29": [
        73626, 
        86407, 
        79905, 
        54536
      ], 
      "3": [
        0, 
        0, 
        0, 
        0
      ], 
      "30": [
        0, 
        0, 
        0, 
        0
      ], 
      "31": [
        52528, 
        43712, 
        52274, 
        18222
      ], 
      "32": [
        116654, 
        138233, 
        126266, 
        160241
      ], 
      "33": [
        0, 
        0, 
        0, 
        0
      ], 
      "34": [
        64126, 
        94521, 
        73992, 
        142019
      ], 
      "35": [
        0, 
        0, 
        0, 
        0
      ], 
      "36": [
        0, 
        0, 
        0, 
        0
      ], 
      "37": [
        0, 
        0, 
        0, 
        0
      ], 
      "38": [
        0, 
        0, 
        0, 
        0
      ], 
      "39": [
        0, 
        0, 
        0, 
        0
      ], 
      "4": [
        0, 
        0, 
        0, 
        0
      ], 
      "40": [
        0, 
        0, 
        0, 
        0
      ], 
      "41": [
        0, 
        0, 
        0, 
        0
      ], 
      "42": [
        0, 
        0, 
        0, 
        0
      ], 
      "43": [
        0, 
        0, 
        0, 
        0
      ], 
      "44": [
        0, 
        0, 
        0, 
        0
      ], 
      "45": [
        0, 
        0, 
        0, 
        0
      ], 
      "46": [
        0, 
        0, 
        0, 
        0
      ], 
      "47": [
        0, 
        0, 
        0, 
        0
      ], 
      "48": [
        9080, 
        7152, 
        8888, 
        2528
      ], 
      "49": [
        2555, 
        7230, 
        3511, 
        12276
      ], 
      "5": [
        0, 
        0, 
        0, 
        0
      ], 
      "50": [
        6084, 
        5284, 
        6122, 
        2561
      ], 
      "51": [
        276, 
        184, 
        310, 
        61
      ], 
      "52": [
        6084, 
        5284, 
        6122, 
        2561
      ], 
      "53": [
        13207, 
        24713, 
        16321, 
        48109
      ], 
      "54": [
        3561, 
        2915, 
        3711, 
        1641
      ], 
      "55": [
        17, 
        16, 
        23, 
        2
      ], 
      "56": [
        2767, 
        2178, 
        2923, 
        1238
      ], 
      "57": [
        1, 
        1, 
        1, 
        1
      ], 
      "58": [
        3, 
        3, 
        3, 
        3
      ], 
      "59": [
        47, 
        47, 
        47, 
        48
      ], 
      "6": [
        0, 
        0, 
        0, 
        0
      ], 
      "60": [
        164, 
        144, 
        181, 
        66
      ], 
      "61": [
        21248, 
        17720, 
        21133, 
        7651
      ], 
      "62": [
        372, 
        372, 
        372, 
        372
      ], 
      "63": [
        0, 
        0, 
        0, 
        8
      ], 
      "7": [
        0, 
        0, 
        0, 
        0
      ], 
      "8": [
        0, 
        0, 
        0, 
        0
      ], 
      "9": [
        0, 
        0, 
        0, 
        0
      ]
    }
  }, 
  "features": {
    "GWS": [
      16, 
      16, 
      64
    ], 
    "LWS": [
      4, 
      1, 
      64
    ], 
    "OFFSET": [
      0, 
      0, 
      0
    ], 
    "compiler name": "ARM Mali OpenCL", 
    "compiler version": "5.0", 
    "cpu_freq": 800, 
    "gpu_freq": 266, 
    "image cols": 2868, 
    "image rows": 1607, 
    "pool_dir": "pool.13", 
    "program version": "c597087", 
    "size": 16
  }, 
  "meta": {
    "device name": "Mali-T604", 
    "device type": "GPU", 
    "device vendor": "ARM", 
    "experiment type": "benchmarking", 
    "kernel name": "calc_histogram", 
    "program name": "Realeyes HOG"
  }, 
  "tags": [
    "demo", 
    "arm", 
    "codegen15"
  ], 
  "work": {
    "repl": 2, 
    "timestamp": "2015-02-22T01:50:56.348866"
  }
}