{
  "characteristics": {
    "cpu": 0.110279, 
    "gpu_copy": 0.060627, 
    "gpu_only": 0.05408, 
    "is_gpu_better": true, 
    "l2 cache and mmu counters": {
      "0": 263132341, 
      "1": 18, 
      "10": 0, 
      "11": 0, 
      "12": 0, 
      "13": 0, 
      "14": 0, 
      "15": 0, 
      "16": 9, 
      "17": 3, 
      "18": 156, 
      "19": 5, 
      "2": 65535, 
      "20": 0, 
      "21": 0, 
      "22": 0, 
      "23": 0, 
      "24": 0, 
      "25": 0, 
      "26": 0, 
      "27": 0, 
      "28": 0, 
      "29": 0, 
      "3": 0, 
      "30": 14248, 
      "31": 103460, 
      "32": 10702877, 
      "33": 8733492, 
      "34": 8708726, 
      "35": 739701, 
      "36": 788143, 
      "37": 8451994, 
      "38": 0, 
      "39": 1167627, 
      "4": 186758, 
      "40": 1135189, 
      "41": 4065, 
      "42": 0, 
      "43": 1163420, 
      "44": 0, 
      "45": 215, 
      "46": 0, 
      "47": 0, 
      "48": 25865, 
      "49": 25865, 
      "5": 16218, 
      "50": 3576, 
      "51": 2909, 
      "52": 10, 
      "53": 2, 
      "54": 0, 
      "55": 0, 
      "56": 0, 
      "57": 336, 
      "58": 0, 
      "59": 0, 
      "6": 67, 
      "60": 0, 
      "61": 230199, 
      "62": 9181465, 
      "63": 6922968, 
      "7": 1783, 
      "8": 15200, 
      "9": 0
    }, 
    "shader core counters": {
      "0": [
        263132341, 
        263132341, 
        263132341, 
        263132341
      ], 
      "1": [
        18, 
        18, 
        18, 
        18
      ], 
      "10": [
        0, 
        0, 
        0, 
        0
      ], 
      "11": [
        0, 
        0, 
        0, 
        0
      ], 
      "12": [
        0, 
        0, 
        0, 
        0
      ], 
      "13": [
        0, 
        0, 
        0, 
        0
      ], 
      "14": [
        0, 
        0, 
        0, 
        0
      ], 
      "15": [
        0, 
        0, 
        0, 
        0
      ], 
      "16": [
        0, 
        0, 
        0, 
        0
      ], 
      "17": [
        0, 
        0, 
        0, 
        0
      ], 
      "18": [
        0, 
        0, 
        0, 
        0
      ], 
      "19": [
        0, 
        0, 
        0, 
        0
      ], 
      "2": [
        65535, 
        65535, 
        65535, 
        65535
      ], 
      "20": [
        0, 
        0, 
        0, 
        0
      ], 
      "21": [
        0, 
        0, 
        0, 
        0
      ], 
      "22": [
        14375100, 
        14380453, 
        14374327, 
        14385032
      ], 
      "23": [
        2429, 
        2103, 
        2367, 
        1293
      ], 
      "24": [
        310912, 
        269184, 
        302976, 
        165504
      ], 
      "25": [
        7510, 
        7997, 
        8225, 
        11268
      ], 
      "26": [
        14374743, 
        14380094, 
        14373974, 
        14384685
      ], 
      "27": [
        7084837, 
        6123808, 
        6910028, 
        3799442
      ], 
      "28": [
        434259, 
        338674, 
        412652, 
        183103
      ], 
      "29": [
        6731245, 
        7292365, 
        6895543, 
        7135647
      ], 
      "3": [
        0, 
        0, 
        0, 
        0
      ], 
      "30": [
        0, 
        0, 
        0, 
        0
      ], 
      "31": [
        4693442, 
        4089216, 
        4579960, 
        2600672
      ], 
      "32": [
        10465801, 
        11764406, 
        10842554, 
        13563134
      ], 
      "33": [
        0, 
        0, 
        0, 
        0
      ], 
      "34": [
        5772359, 
        7675190, 
        6262594, 
        10962462
      ], 
      "35": [
        0, 
        0, 
        0, 
        0
      ], 
      "36": [
        0, 
        0, 
        0, 
        0
      ], 
      "37": [
        0, 
        0, 
        0, 
        0
      ], 
      "38": [
        0, 
        0, 
        0, 
        0
      ], 
      "39": [
        0, 
        0, 
        0, 
        0
      ], 
      "4": [
        0, 
        0, 
        0, 
        0
      ], 
      "40": [
        0, 
        0, 
        0, 
        0
      ], 
      "41": [
        0, 
        0, 
        0, 
        0
      ], 
      "42": [
        0, 
        0, 
        0, 
        0
      ], 
      "43": [
        0, 
        0, 
        0, 
        0
      ], 
      "44": [
        0, 
        0, 
        0, 
        0
      ], 
      "45": [
        0, 
        0, 
        0, 
        0
      ], 
      "46": [
        0, 
        0, 
        0, 
        0
      ], 
      "47": [
        0, 
        0, 
        0, 
        0
      ], 
      "48": [
        729604, 
        627828, 
        710434, 
        385382
      ], 
      "49": [
        286844, 
        618533, 
        405424, 
        1343518
      ], 
      "5": [
        0, 
        0, 
        0, 
        0
      ], 
      "50": [
        609343, 
        536551, 
        595714, 
        351933
      ], 
      "51": [
        29658, 
        22926, 
        28292, 
        11091
      ], 
      "52": [
        609343, 
        536551, 
        595714, 
        351933
      ], 
      "53": [
        1030027, 
        1754737, 
        1172295, 
        3022301
      ], 
      "54": [
        326573, 
        291102, 
        324040, 
        200273
      ], 
      "55": [
        2207, 
        1210, 
        4095, 
        2356
      ], 
      "56": [
        228506, 
        204701, 
        221470, 
        136684
      ], 
      "57": [
        1, 
        1, 
        1, 
        1
      ], 
      "58": [
        3, 
        3, 
        3, 
        3
      ], 
      "59": [
        47, 
        49, 
        47, 
        49
      ], 
      "6": [
        0, 
        0, 
        0, 
        0
      ], 
      "60": [
        26281, 
        22983, 
        25550, 
        14398
      ], 
      "61": [
        1948291, 
        1700930, 
        1901863, 
        1089249
      ], 
      "62": [
        372, 
        372, 
        372, 
        372
      ], 
      "63": [
        0, 
        24, 
        0, 
        24
      ], 
      "7": [
        0, 
        0, 
        0, 
        0
      ], 
      "8": [
        0, 
        0, 
        0, 
        0
      ], 
      "9": [
        0, 
        0, 
        0, 
        0
      ]
    }
  }, 
  "features": {
    "GWS": [
      12, 
      12, 
      64
    ], 
    "LWS": [
      4, 
      1, 
      64
    ], 
    "OFFSET": [
      0, 
      0, 
      0
    ], 
    "compiler name": "ARM Mali OpenCL", 
    "compiler version": "5.0", 
    "cpu_freq": 1600, 
    "gpu_freq": 266, 
    "image cols": 2174, 
    "image rows": 2215, 
    "pool_dir": "pool.00", 
    "program version": "c597087", 
    "size": 128
  }, 
  "meta": {
    "device name": "Mali-T604", 
    "device type": "GPU", 
    "device vendor": "ARM", 
    "experiment type": "benchmarking", 
    "kernel name": "calc_histogram", 
    "program name": "Realeyes HOG"
  }, 
  "tags": [
    "demo", 
    "arm", 
    "codegen15"
  ], 
  "work": {
    "repl": 4, 
    "timestamp": "2015-02-22T02:14:14.243353"
  }
}