{
  "characteristics": {
    "cpu": 0.021614, 
    "gpu_copy": 0.01288, 
    "gpu_only": 0.011059, 
    "is_gpu_better": true, 
    "l2 cache and mmu counters": {
      "0": 938491483, 
      "1": 14, 
      "10": 0, 
      "11": 0, 
      "12": 0, 
      "13": 0, 
      "14": 0, 
      "15": 0, 
      "16": 9, 
      "17": 3, 
      "18": 148, 
      "19": 7, 
      "2": 65535, 
      "20": 0, 
      "21": 0, 
      "22": 0, 
      "23": 0, 
      "24": 0, 
      "25": 0, 
      "26": 0, 
      "27": 0, 
      "28": 0, 
      "29": 0, 
      "3": 0, 
      "30": 1871, 
      "31": 16064, 
      "32": 2182984, 
      "33": 1801268, 
      "34": 1799084, 
      "35": 149496, 
      "36": 163412, 
      "37": 1747085, 
      "38": 0, 
      "39": 213122, 
      "4": 149, 
      "40": 206711, 
      "41": 499, 
      "42": 0, 
      "43": 212706, 
      "44": 0, 
      "45": 47, 
      "46": 0, 
      "47": 0, 
      "48": 4016, 
      "49": 4016, 
      "5": 57, 
      "50": 472, 
      "51": 438, 
      "52": 5, 
      "53": 2, 
      "54": 0, 
      "55": 0, 
      "56": 0, 
      "57": 22, 
      "58": 0, 
      "59": 0, 
      "6": 0, 
      "60": 0, 
      "61": 49374, 
      "62": 1871734, 
      "63": 1511220, 
      "7": 84, 
      "8": 39, 
      "9": 0
    }, 
    "shader core counters": {
      "0": [
        938491483, 
        938491483, 
        938491483, 
        938491483
      ], 
      "1": [
        14, 
        14, 
        14, 
        14
      ], 
      "10": [
        0, 
        0, 
        0, 
        0
      ], 
      "11": [
        0, 
        0, 
        0, 
        0
      ], 
      "12": [
        0, 
        0, 
        0, 
        0
      ], 
      "13": [
        0, 
        0, 
        0, 
        0
      ], 
      "14": [
        0, 
        0, 
        0, 
        0
      ], 
      "15": [
        0, 
        0, 
        0, 
        0
      ], 
      "16": [
        0, 
        0, 
        0, 
        0
      ], 
      "17": [
        0, 
        0, 
        0, 
        0
      ], 
      "18": [
        0, 
        0, 
        0, 
        0
      ], 
      "19": [
        0, 
        0, 
        0, 
        0
      ], 
      "2": [
        65535, 
        65535, 
        65535, 
        65535
      ], 
      "20": [
        0, 
        0, 
        0, 
        0
      ], 
      "21": [
        0, 
        0, 
        0, 
        0
      ], 
      "22": [
        2939183, 
        2934824, 
        2940669, 
        2941546
      ], 
      "23": [
        642, 
        540, 
        626, 
        240
      ], 
      "24": [
        82176, 
        69120, 
        80128, 
        30720
      ], 
      "25": [
        6815, 
        10157, 
        6665, 
        39013
      ], 
      "26": [
        2938831, 
        2934472, 
        2940322, 
        2941205
      ], 
      "27": [
        1467022, 
        1237624, 
        1428206, 
        555198
      ], 
      "28": [
        89142, 
        64557, 
        84382, 
        26433
      ], 
      "29": [
        1353446, 
        1523416, 
        1394735, 
        1378381
      ], 
      "3": [
        0, 
        0, 
        0, 
        0
      ], 
      "30": [
        0, 
        0, 
        0, 
        0
      ], 
      "31": [
        978082, 
        834186, 
        955234, 
        401614
      ], 
      "32": [
        2084736, 
        2395087, 
        2163163, 
        2846204
      ], 
      "33": [
        0, 
        0, 
        0, 
        0
      ], 
      "34": [
        1106654, 
        1560901, 
        1207929, 
        2444590
      ], 
      "35": [
        0, 
        0, 
        0, 
        0
      ], 
      "36": [
        0, 
        0, 
        0, 
        0
      ], 
      "37": [
        0, 
        0, 
        0, 
        0
      ], 
      "38": [
        0, 
        0, 
        0, 
        0
      ], 
      "39": [
        0, 
        0, 
        0, 
        0
      ], 
      "4": [
        0, 
        0, 
        0, 
        0
      ], 
      "40": [
        0, 
        0, 
        0, 
        0
      ], 
      "41": [
        0, 
        0, 
        0, 
        0
      ], 
      "42": [
        0, 
        0, 
        0, 
        0
      ], 
      "43": [
        0, 
        0, 
        0, 
        0
      ], 
      "44": [
        0, 
        0, 
        0, 
        0
      ], 
      "45": [
        0, 
        0, 
        0, 
        0
      ], 
      "46": [
        0, 
        0, 
        0, 
        0
      ], 
      "47": [
        0, 
        0, 
        0, 
        0
      ], 
      "48": [
        159872, 
        133888, 
        155408, 
        57840
      ], 
      "49": [
        42199, 
        100453, 
        54180, 
        191800
      ], 
      "5": [
        0, 
        0, 
        0, 
        0
      ], 
      "50": [
        120276, 
        104378, 
        117940, 
        55091
      ], 
      "51": [
        5692, 
        4271, 
        5529, 
        1345
      ], 
      "52": [
        120276, 
        104378, 
        117940, 
        55091
      ], 
      "53": [
        219016, 
        404156, 
        257375, 
        833544
      ], 
      "54": [
        60907, 
        54146, 
        60862, 
        31028
      ], 
      "55": [
        382, 
        244, 
        313, 
        96
      ], 
      "56": [
        47907, 
        42915, 
        48010, 
        24700
      ], 
      "57": [
        1, 
        1, 
        1, 
        1
      ], 
      "58": [
        3, 
        3, 
        3, 
        3
      ], 
      "59": [
        48, 
        49, 
        47, 
        47
      ], 
      "6": [
        0, 
        0, 
        0, 
        0
      ], 
      "60": [
        15, 
        17, 
        15, 
        17
      ], 
      "61": [
        400425, 
        342645, 
        391289, 
        168023
      ], 
      "62": [
        372, 
        372, 
        372, 
        372
      ], 
      "63": [
        16, 
        24, 
        0, 
        8
      ], 
      "7": [
        0, 
        0, 
        0, 
        0
      ], 
      "8": [
        0, 
        0, 
        0, 
        0
      ], 
      "9": [
        0, 
        0, 
        0, 
        0
      ]
    }
  }, 
  "features": {
    "GWS": [
      64, 
      64, 
      64
    ], 
    "LWS": [
      4, 
      1, 
      64
    ], 
    "OFFSET": [
      0, 
      0, 
      0
    ], 
    "compiler name": "ARM Mali OpenCL", 
    "compiler version": "5.0", 
    "cpu_freq": 1600, 
    "gpu_freq": 266, 
    "image cols": 816, 
    "image rows": 612, 
    "pool_dir": "pool.21", 
    "program version": "c597087", 
    "size": 64
  }, 
  "meta": {
    "device name": "Mali-T604", 
    "device type": "GPU", 
    "device vendor": "ARM", 
    "experiment type": "benchmarking", 
    "kernel name": "calc_histogram", 
    "program name": "Realeyes HOG"
  }, 
  "tags": [
    "demo", 
    "arm", 
    "codegen15"
  ], 
  "work": {
    "repl": 3, 
    "timestamp": "2015-02-22T02:02:46.481208"
  }
}