{
  "characteristics": {
    "cpu": 0.159852, 
    "gpu_copy": 0.049682, 
    "gpu_only": 0.04609, 
    "is_gpu_better": true, 
    "l2 cache and mmu counters": {
      "0": 911029382, 
      "1": 16, 
      "10": 0, 
      "11": 0, 
      "12": 0, 
      "13": 0, 
      "14": 0, 
      "15": 0, 
      "16": 8, 
      "17": 3, 
      "18": 131, 
      "19": 4, 
      "2": 65535, 
      "20": 0, 
      "21": 0, 
      "22": 0, 
      "23": 0, 
      "24": 0, 
      "25": 0, 
      "26": 0, 
      "27": 0, 
      "28": 0, 
      "29": 0, 
      "3": 0, 
      "30": 5889, 
      "31": 45664, 
      "32": 9069104, 
      "33": 7492653, 
      "34": 7486664, 
      "35": 619103, 
      "36": 675795, 
      "37": 7255045, 
      "38": 0, 
      "39": 891807, 
      "4": 131, 
      "40": 865228, 
      "41": 1798, 
      "42": 0, 
      "43": 890076, 
      "44": 0, 
      "45": 100, 
      "46": 0, 
      "47": 0, 
      "48": 11416, 
      "49": 11416, 
      "5": 52, 
      "50": 1478, 
      "51": 1358, 
      "52": 7, 
      "53": 2, 
      "54": 0, 
      "55": 0, 
      "56": 0, 
      "57": 89, 
      "58": 0, 
      "59": 0, 
      "6": 40, 
      "60": 0, 
      "61": 223264, 
      "62": 7756948, 
      "63": 6285282, 
      "7": 67, 
      "8": 35, 
      "9": 0
    }, 
    "shader core counters": {
      "0": [
        911029382, 
        911029382, 
        911029382, 
        911029382
      ], 
      "1": [
        16, 
        16, 
        16, 
        16
      ], 
      "10": [
        0, 
        0, 
        0, 
        0
      ], 
      "11": [
        0, 
        0, 
        0, 
        0
      ], 
      "12": [
        0, 
        0, 
        0, 
        0
      ], 
      "13": [
        0, 
        0, 
        0, 
        0
      ], 
      "14": [
        0, 
        0, 
        0, 
        0
      ], 
      "15": [
        0, 
        0, 
        0, 
        0
      ], 
      "16": [
        0, 
        0, 
        0, 
        0
      ], 
      "17": [
        0, 
        0, 
        0, 
        0
      ], 
      "18": [
        0, 
        0, 
        0, 
        0
      ], 
      "19": [
        0, 
        0, 
        0, 
        0
      ], 
      "2": [
        65535, 
        65535, 
        65535, 
        65535
      ], 
      "20": [
        0, 
        0, 
        0, 
        0
      ], 
      "21": [
        0, 
        0, 
        0, 
        0
      ], 
      "22": [
        12255014, 
        12252206, 
        12256357, 
        12260016
      ], 
      "23": [
        2731, 
        2058, 
        2620, 
        783
      ], 
      "24": [
        349568, 
        263424, 
        335360, 
        100224
      ], 
      "25": [
        171703, 
        257542, 
        158100, 
        489109
      ], 
      "26": [
        12254672, 
        12251864, 
        12256010, 
        12259672
      ], 
      "27": [
        6035887, 
        4581297, 
        5844920, 
        1854478
      ], 
      "28": [
        359519, 
        222676, 
        335836, 
        95386
      ], 
      "29": [
        5748958, 
        6627480, 
        5955781, 
        5177055
      ], 
      "3": [
        0, 
        0, 
        0, 
        0
      ], 
      "30": [
        0, 
        0, 
        0, 
        0
      ], 
      "31": [
        4050496, 
        3128666, 
        3932114, 
        1355082
      ], 
      "32": [
        8739828, 
        10569943, 
        9132317, 
        12028874
      ], 
      "33": [
        0, 
        0, 
        0, 
        0
      ], 
      "34": [
        4689332, 
        7441277, 
        5200203, 
        10673792
      ], 
      "35": [
        0, 
        0, 
        0, 
        0
      ], 
      "36": [
        0, 
        0, 
        0, 
        0
      ], 
      "37": [
        0, 
        0, 
        0, 
        0
      ], 
      "38": [
        0, 
        0, 
        0, 
        0
      ], 
      "39": [
        0, 
        0, 
        0, 
        0
      ], 
      "4": [
        0, 
        0, 
        0, 
        0
      ], 
      "40": [
        0, 
        0, 
        0, 
        0
      ], 
      "41": [
        0, 
        0, 
        0, 
        0
      ], 
      "42": [
        0, 
        0, 
        0, 
        0
      ], 
      "43": [
        0, 
        0, 
        0, 
        0
      ], 
      "44": [
        0, 
        0, 
        0, 
        0
      ], 
      "45": [
        0, 
        0, 
        0, 
        0
      ], 
      "46": [
        0, 
        0, 
        0, 
        0
      ], 
      "47": [
        0, 
        0, 
        0, 
        0
      ], 
      "48": [
        659810, 
        495282, 
        637980, 
        193232
      ], 
      "49": [
        188025, 
        533118, 
        256516, 
        910382
      ], 
      "5": [
        0, 
        0, 
        0, 
        0
      ], 
      "50": [
        498558, 
        395949, 
        486469, 
        188540
      ], 
      "51": [
        25180, 
        15830, 
        23507, 
        4007
      ], 
      "52": [
        498558, 
        395949, 
        486469, 
        188540
      ], 
      "53": [
        944923, 
        2082633, 
        1135766, 
        3568348
      ], 
      "54": [
        272372, 
        219192, 
        263598, 
        112284
      ], 
      "55": [
        1924, 
        1484, 
        1427, 
        440
      ], 
      "56": [
        212570, 
        169673, 
        206747, 
        87331
      ], 
      "57": [
        1, 
        1, 
        1, 
        1
      ], 
      "58": [
        3, 
        3, 
        3, 
        3
      ], 
      "59": [
        47, 
        47, 
        49, 
        47
      ], 
      "6": [
        0, 
        0, 
        0, 
        0
      ], 
      "60": [
        14, 
        14, 
        14, 
        14
      ], 
      "61": [
        1656927, 
        1287180, 
        1610919, 
        570313
      ], 
      "62": [
        372, 
        372, 
        372, 
        372
      ], 
      "63": [
        8, 
        0, 
        24, 
        0
      ], 
      "7": [
        0, 
        0, 
        0, 
        0
      ], 
      "8": [
        0, 
        0, 
        0, 
        0
      ], 
      "9": [
        0, 
        0, 
        0, 
        0
      ]
    }
  }, 
  "features": {
    "GWS": [
      12, 
      12, 
      64
    ], 
    "LWS": [
      4, 
      1, 
      64
    ], 
    "OFFSET": [
      0, 
      0, 
      0
    ], 
    "compiler name": "ARM Mali OpenCL", 
    "compiler version": "5.0", 
    "cpu_freq": 800, 
    "gpu_freq": 266, 
    "image cols": 633, 
    "image rows": 921, 
    "pool_dir": "pool.01", 
    "program version": "c597087", 
    "size": 128
  }, 
  "meta": {
    "device name": "Mali-T604", 
    "device type": "GPU", 
    "device vendor": "ARM", 
    "experiment type": "benchmarking", 
    "kernel name": "calc_histogram", 
    "program name": "Realeyes HOG"
  }, 
  "tags": [
    "demo", 
    "arm", 
    "codegen15"
  ], 
  "work": {
    "repl": 2, 
    "timestamp": "2015-02-22T02:08:43.384005"
  }
}