{
  "characteristics": {
    "cpu": 0.027545, 
    "gpu_copy": 0.044021, 
    "gpu_only": 0.036568, 
    "is_gpu_better": false, 
    "l2 cache and mmu counters": {
      "0": 1198886447, 
      "1": 16, 
      "10": 0, 
      "11": 0, 
      "12": 0, 
      "13": 0, 
      "14": 0, 
      "15": 0, 
      "16": 9, 
      "17": 3, 
      "18": 223, 
      "19": 7, 
      "2": 65535, 
      "20": 0, 
      "21": 0, 
      "22": 0, 
      "23": 0, 
      "24": 0, 
      "25": 0, 
      "26": 0, 
      "27": 0, 
      "28": 0, 
      "29": 0, 
      "3": 0, 
      "30": 1632, 
      "31": 107642, 
      "32": 6170902, 
      "33": 4847972, 
      "34": 4847041, 
      "35": 462976, 
      "36": 522671, 
      "37": 4655633, 
      "38": 0, 
      "39": 790415, 
      "4": 180959, 
      "40": 790404, 
      "41": 3681, 
      "42": 0, 
      "43": 789195, 
      "44": 0, 
      "45": 258, 
      "46": 0, 
      "47": 0, 
      "48": 26910, 
      "49": 26910, 
      "5": 199, 
      "50": 413, 
      "51": 407, 
      "52": 6, 
      "53": 2, 
      "54": 0, 
      "55": 0, 
      "56": 0, 
      "57": 618, 
      "58": 1, 
      "59": 0, 
      "6": 76, 
      "60": 0, 
      "61": 130938, 
      "62": 5224266, 
      "63": 1960054, 
      "7": 325, 
      "8": 151, 
      "9": 0
    }, 
    "shader core counters": {
      "0": [
        1198886447, 
        1198886447, 
        1198886447, 
        1198886447
      ], 
      "1": [
        16, 
        16, 
        16, 
        16
      ], 
      "10": [
        0, 
        0, 
        0, 
        0
      ], 
      "11": [
        0, 
        0, 
        0, 
        0
      ], 
      "12": [
        0, 
        0, 
        0, 
        0
      ], 
      "13": [
        0, 
        0, 
        0, 
        0
      ], 
      "14": [
        0, 
        0, 
        0, 
        0
      ], 
      "15": [
        0, 
        0, 
        0, 
        0
      ], 
      "16": [
        0, 
        0, 
        0, 
        0
      ], 
      "17": [
        0, 
        0, 
        0, 
        0
      ], 
      "18": [
        0, 
        0, 
        0, 
        0
      ], 
      "19": [
        0, 
        0, 
        0, 
        0
      ], 
      "2": [
        65535, 
        65535, 
        65535, 
        65535
      ], 
      "20": [
        0, 
        0, 
        0, 
        0
      ], 
      "21": [
        0, 
        0, 
        0, 
        0
      ], 
      "22": [
        9721610, 
        9719421, 
        9726724, 
        9719111
      ], 
      "23": [
        2041, 
        2056, 
        2067, 
        2028
      ], 
      "24": [
        261248, 
        263168, 
        264576, 
        259584
      ], 
      "25": [
        3802, 
        5414, 
        4562, 
        4718
      ], 
      "26": [
        9721238, 
        9719039, 
        9726347, 
        9718736
      ], 
      "27": [
        5887294, 
        5839114, 
        5897316, 
        5855710
      ], 
      "28": [
        168695, 
        166289, 
        169015, 
        167091
      ], 
      "29": [
        3578182, 
        3606791, 
        3577781, 
        3603809
      ], 
      "3": [
        0, 
        0, 
        0, 
        0
      ], 
      "30": [
        0, 
        0, 
        0, 
        0
      ], 
      "31": [
        2131418, 
        2118330, 
        2137271, 
        2117651
      ], 
      "32": [
        5437317, 
        5528105, 
        5411372, 
        5492723
      ], 
      "33": [
        0, 
        0, 
        0, 
        0
      ], 
      "34": [
        3305899, 
        3409775, 
        3274101, 
        3375072
      ], 
      "35": [
        0, 
        0, 
        0, 
        0
      ], 
      "36": [
        0, 
        0, 
        0, 
        0
      ], 
      "37": [
        0, 
        0, 
        0, 
        0
      ], 
      "38": [
        0, 
        0, 
        0, 
        0
      ], 
      "39": [
        0, 
        0, 
        0, 
        0
      ], 
      "4": [
        0, 
        0, 
        0, 
        0
      ], 
      "40": [
        0, 
        0, 
        0, 
        0
      ], 
      "41": [
        0, 
        0, 
        0, 
        0
      ], 
      "42": [
        0, 
        0, 
        0, 
        0
      ], 
      "43": [
        0, 
        0, 
        0, 
        0
      ], 
      "44": [
        0, 
        0, 
        0, 
        0
      ], 
      "45": [
        0, 
        0, 
        0, 
        0
      ], 
      "46": [
        0, 
        0, 
        0, 
        0
      ], 
      "47": [
        0, 
        0, 
        0, 
        0
      ], 
      "48": [
        521698, 
        516580, 
        522702, 
        518687
      ], 
      "49": [
        228644, 
        238344, 
        225600, 
        242588
      ], 
      "5": [
        0, 
        0, 
        0, 
        0
      ], 
      "50": [
        0, 
        0, 
        0, 
        0
      ], 
      "51": [
        0, 
        0, 
        0, 
        0
      ], 
      "52": [
        525137, 
        521709, 
        525659, 
        521493
      ], 
      "53": [
        1281019, 
        1324937, 
        1268372, 
        1302402
      ], 
      "54": [
        200792, 
        198498, 
        198361, 
        200524
      ], 
      "55": [
        129789, 
        128949, 
        128316, 
        129265
      ], 
      "56": [
        133242, 
        132446, 
        131737, 
        132720
      ], 
      "57": [
        1, 
        1, 
        1, 
        1
      ], 
      "58": [
        4, 
        4, 
        4, 
        4
      ], 
      "59": [
        43, 
        42, 
        42, 
        43
      ], 
      "6": [
        0, 
        0, 
        0, 
        0
      ], 
      "60": [
        18202, 
        17996, 
        17974, 
        18585
      ], 
      "61": [
        1139505, 
        1129981, 
        1141147, 
        1132261
      ], 
      "62": [
        332, 
        332, 
        332, 
        332
      ], 
      "63": [
        8, 
        0, 
        0, 
        16
      ], 
      "7": [
        0, 
        0, 
        0, 
        0
      ], 
      "8": [
        0, 
        0, 
        0, 
        0
      ], 
      "9": [
        0, 
        0, 
        0, 
        0
      ]
    }
  }, 
  "features": {
    "GWS": [
      12, 
      12, 
      64
    ], 
    "LWS": [
      4, 
      1, 
      64
    ], 
    "OFFSET": [
      0, 
      0, 
      0
    ], 
    "compiler name": "ARM Mali OpenCL", 
    "compiler version": "5.0", 
    "cpu_freq": 1600, 
    "gpu_freq": 266, 
    "image cols": 2103, 
    "image rows": 2082, 
    "pool_dir": "pool.18", 
    "program version": "c597087", 
    "size": 128
  }, 
  "meta": {
    "device name": "Mali-T628", 
    "device type": "GPU", 
    "device vendor": "ARM", 
    "experiment type": "benchmarking", 
    "kernel name": "calc_histogram", 
    "program name": "Realeyes HOG"
  }, 
  "tags": [
    "demo", 
    "arm", 
    "codegen15"
  ], 
  "work": {
    "repl": 4, 
    "timestamp": "2015-02-22T02:00:21.136678"
  }
}