{
  "characteristics": {
    "cpu": 0.015789, 
    "gpu_copy": 0.016222, 
    "gpu_only": 0.004571, 
    "is_gpu_better": false, 
    "l2 cache and mmu counters": {
      "0": 257290801, 
      "1": 20, 
      "10": 0, 
      "11": 0, 
      "12": 0, 
      "13": 0, 
      "14": 0, 
      "15": 0, 
      "16": 9, 
      "17": 3, 
      "18": 262, 
      "19": 7, 
      "2": 65535, 
      "20": 0, 
      "21": 0, 
      "22": 0, 
      "23": 0, 
      "24": 0, 
      "25": 0, 
      "26": 0, 
      "27": 0, 
      "28": 0, 
      "29": 0, 
      "3": 0, 
      "30": 524, 
      "31": 34138, 
      "32": 1531387, 
      "33": 0, 
      "34": 1204351, 
      "35": 114615, 
      "36": 130106, 
      "37": 1152409, 
      "38": 0, 
      "39": 190111, 
      "4": 45567, 
      "40": 190106, 
      "41": 1009, 
      "42": 0, 
      "43": 189832, 
      "44": 0, 
      "45": 149, 
      "46": 0, 
      "47": 0, 
      "48": 8534, 
      "49": 8534, 
      "5": 176, 
      "50": 136, 
      "51": 130, 
      "52": 6, 
      "53": 2, 
      "54": 0, 
      "55": 0, 
      "56": 0, 
      "57": 317, 
      "58": 0, 
      "59": 0, 
      "6": 82, 
      "60": 0, 
      "61": 31915, 
      "62": 1293067, 
      "63": 503400, 
      "7": 525, 
      "8": 132, 
      "9": 0
    }, 
    "shader core counters": {
      "0": [
        257290801, 
        257290801, 
        257290801, 
        257290801
      ], 
      "1": [
        20, 
        20, 
        20, 
        20
      ], 
      "10": [
        0, 
        0, 
        0, 
        0
      ], 
      "11": [
        0, 
        0, 
        0, 
        0
      ], 
      "12": [
        0, 
        0, 
        0, 
        0
      ], 
      "13": [
        0, 
        0, 
        0, 
        0
      ], 
      "14": [
        0, 
        0, 
        0, 
        0
      ], 
      "15": [
        0, 
        0, 
        0, 
        0
      ], 
      "16": [
        0, 
        0, 
        0, 
        0
      ], 
      "17": [
        0, 
        0, 
        0, 
        0
      ], 
      "18": [
        0, 
        0, 
        0, 
        0
      ], 
      "19": [
        0, 
        0, 
        0, 
        0
      ], 
      "2": [
        65535, 
        65535, 
        65535, 
        65535
      ], 
      "20": [
        0, 
        0, 
        0, 
        0
      ], 
      "21": [
        0, 
        0, 
        0, 
        0
      ], 
      "22": [
        2427990, 
        2430647, 
        2431395, 
        2431346
      ], 
      "23": [
        513, 
        500, 
        525, 
        510
      ], 
      "24": [
        65664, 
        64000, 
        67200, 
        65280
      ], 
      "25": [
        4588, 
        4650, 
        4331, 
        4269
      ], 
      "26": [
        2427535, 
        2430185, 
        2430939, 
        2430893
      ], 
      "27": [
        1465600, 
        1451210, 
        1471220, 
        1459388
      ], 
      "28": [
        41902, 
        41220, 
        42273, 
        41490
      ], 
      "29": [
        888502, 
        905346, 
        887198, 
        901274
      ], 
      "3": [
        0, 
        0, 
        0, 
        0
      ], 
      "30": [
        0, 
        0, 
        0, 
        0
      ], 
      "31": [
        530926, 
        525094, 
        534210, 
        528264
      ], 
      "32": [
        1366697, 
        1378647, 
        1350894, 
        1377220
      ], 
      "33": [
        0, 
        0, 
        0, 
        0
      ], 
      "34": [
        835771, 
        853553, 
        816684, 
        848956
      ], 
      "35": [
        0, 
        0, 
        0, 
        0
      ], 
      "36": [
        0, 
        0, 
        0, 
        0
      ], 
      "37": [
        0, 
        0, 
        0, 
        0
      ], 
      "38": [
        0, 
        0, 
        0, 
        0
      ], 
      "39": [
        0, 
        0, 
        0, 
        0
      ], 
      "4": [
        0, 
        0, 
        0, 
        0
      ], 
      "40": [
        0, 
        0, 
        0, 
        0
      ], 
      "41": [
        0, 
        0, 
        0, 
        0
      ], 
      "42": [
        0, 
        0, 
        0, 
        0
      ], 
      "43": [
        0, 
        0, 
        0, 
        0
      ], 
      "44": [
        0, 
        0, 
        0, 
        0
      ], 
      "45": [
        0, 
        0, 
        0, 
        0
      ], 
      "46": [
        0, 
        0, 
        0, 
        0
      ], 
      "47": [
        0, 
        0, 
        0, 
        0
      ], 
      "48": [
        129843, 
        128749, 
        130325, 
        129317
      ], 
      "49": [
        58431, 
        61761, 
        58959, 
        59787
      ], 
      "5": [
        0, 
        0, 
        0, 
        0
      ], 
      "50": [
        0, 
        0, 
        0, 
        0
      ], 
      "51": [
        0, 
        0, 
        0, 
        0
      ], 
      "52": [
        130527, 
        129307, 
        131085, 
        129832
      ], 
      "53": [
        322483, 
        328229, 
        312120, 
        327909
      ], 
      "54": [
        48189, 
        48682, 
        47633, 
        48515
      ], 
      "55": [
        32064, 
        32022, 
        31707, 
        32177
      ], 
      "56": [
        33183, 
        33190, 
        32869, 
        33272
      ], 
      "57": [
        1, 
        1, 
        1, 
        1
      ], 
      "58": [
        3, 
        3, 
        3, 
        3
      ], 
      "59": [
        42, 
        44, 
        42, 
        42
      ], 
      "6": [
        0, 
        0, 
        0, 
        0
      ], 
      "60": [
        4526, 
        4635, 
        4522, 
        4633
      ], 
      "61": [
        283407, 
        280891, 
        284461, 
        282040
      ], 
      "62": [
        332, 
        0, 
        332, 
        332
      ], 
      "63": [
        0, 
        24, 
        0, 
        0
      ], 
      "7": [
        0, 
        0, 
        0, 
        0
      ], 
      "8": [
        0, 
        0, 
        0, 
        0
      ], 
      "9": [
        0, 
        0, 
        0, 
        0
      ]
    }
  }, 
  "features": {
    "GWS": [
      64, 
      64, 
      64
    ], 
    "LWS": [
      4, 
      1, 
      64
    ], 
    "OFFSET": [
      0, 
      0, 
      0
    ], 
    "compiler name": "ARM Mali OpenCL", 
    "compiler version": "5.0", 
    "cpu_freq": 800, 
    "gpu_freq": 533, 
    "image cols": 2103, 
    "image rows": 2082, 
    "pool_dir": "pool.18", 
    "program version": "c597087", 
    "size": 64
  }, 
  "meta": {
    "device name": "Mali-T628", 
    "device type": "GPU", 
    "device vendor": "ARM", 
    "experiment type": "benchmarking", 
    "kernel name": "calc_histogram", 
    "program name": "Realeyes HOG"
  }, 
  "tags": [
    "demo", 
    "arm", 
    "codegen15"
  ], 
  "work": {
    "repl": 0, 
    "timestamp": "2015-02-22T02:11:37.888011"
  }
}